setup.py
synaptical/__init__.py
synaptical.egg-info/PKG-INFO
synaptical.egg-info/SOURCES.txt
synaptical.egg-info/dependency_links.txt
synaptical.egg-info/top_level.txt