Metadata-Version: 2.1
Name: synaptical
Version: 0.0.1
Summary: synaptical
Author: shobrook
Author-email: shobrookj@gmail.com
